odoo/addons/stock_picking_batch_report/README.rst
odoo/addons/stock_picking_batch_report/__init__.py
odoo/addons/stock_picking_batch_report/__manifest__.py
odoo/addons/stock_picking_batch_report/i18n/it.po
odoo/addons/stock_picking_batch_report/i18n/stock_picking_batch_report.pot
odoo/addons/stock_picking_batch_report/models/__init__.py
odoo/addons/stock_picking_batch_report/models/stock_picking_batch.py
odoo/addons/stock_picking_batch_report/readme/CONTRIBUTORS.md
odoo/addons/stock_picking_batch_report/readme/DESCRIPTION.md
odoo/addons/stock_picking_batch_report/readme/USAGE.md
odoo/addons/stock_picking_batch_report/reports/report_picking_batch.xml
odoo/addons/stock_picking_batch_report/static/description/icon.png
odoo/addons/stock_picking_batch_report/static/description/index.html
odoo_addon_stock_picking_batch_report-18.0.1.0.0.2.dist-info/METADATA
odoo_addon_stock_picking_batch_report-18.0.1.0.0.2.dist-info/WHEEL
odoo_addon_stock_picking_batch_report-18.0.1.0.0.2.dist-info/top_level.txt
odoo_addon_stock_picking_batch_report-18.0.1.0.0.2.dist-info/RECORD
